{
    "华兴源创": "sh688001",
    "睿创微纳": "sh688002",
    "天准科技": "sh688003",
    "博汇科技": "sh688004",
    "容百科技": "sh688005",
    "杭可科技": "sh688006",
    "光峰科技": "sh688007",
    "澜起科技": "sh688008",
    "中国通号": "sh688009",
    "福光股份": "sh688010",
    "新光光电": "sh688011",
    "中微公司": "sh688012",
    "天臣医疗": "sh688013",
    "交控科技": "sh688015",
    "心脉医疗": "sh688016",
    "绿的谐波": "sh688017",
    "乐鑫科技": "sh688018",
    "安集科技": "sh688019",
    "方邦股份": "sh688020",
    "奥福环保": "sh688021",
    "瀚川智能": "sh688022",
    "安恒信息": "sh688023",
    "杰普特": "sh688025",
    "洁特生物": "sh688026",
    "国盾量子": "sh688027",
    "沃尔德": "sh688028",
    "南微医学": "sh688029",
    "山石网科": "sh688030",
    "禾迈股份": "sh688032",
    "天宜上佳": "sh688033",
    "传音控股": "sh688036",
    "芯源微": "sh688037",
    "中科通达": "sh688038",
    "当虹科技": "sh688039",
    "炬芯科技": "sh688049",
    "爱博医疗": "sh688050",
    "佳华科技": "sh688051",
    "龙腾光电": "sh688055",
    "莱伯泰科": "sh688056",
    "金达莱": "sh688057",
    "宝兰德": "sh688058",
    "华锐精密": "sh688059",
    "云涌科技": "sh688060",
    "迈威生物": "sh688062",
    "派能科技": "sh688063",
    "凯赛生物": "sh688065",
    "航天宏图": "sh688066",
    "爱威科技": "sh688067",
    "热景生物": "sh688068",
    "德林海": "sh688069",
    "纵横股份": "sh688070",
    "华依科技": "sh688071",
    "安旭生物": "sh688075",
    "诺泰生物": "sh688076",
    "大地熊": "sh688077",
    "龙软科技": "sh688078",
    "美迪凯": "sh688079",
    "映翰通": "sh688080",
    "兴图新科": "sh688081",
    "盛美上海": "sh688082",
    "中望软件": "sh688083",
    "三友医疗": "sh688085",
    "紫晶存储": "sh688086",
    "英科再生": "sh688087",
    "虹软科技": "sh688088",
    "嘉必优": "sh688089",
    "瑞松科技": "sh688090",
    "上海谊众": "sh688091",
    "爱科科技": "sh688092",
    "世华科技": "sh688093",
    "福昕软件": "sh688095",
    "京源环保": "sh688096",
    "博众精工": "sh688097",
    "申联生物": "sh688098",
    "晶晨股份": "sh688099",
    "威胜信息": "sh688100",
    "三达膜": "sh688101",
    "斯瑞新材": "sh688102",
    "国力股份": "sh688103",
    "诺唯赞": "sh688105",
    "金宏气体": "sh688106",
    "安路科技": "sh688107",
    "赛诺医疗": "sh688108",
    "品茗股份": "sh688109",
    "东芯股份": "sh688110",
    "金山办公": "sh688111",
    "鼎阳科技": "sh688112",
    "联测科技": "sh688113",
    "思林杰": "sh688115",
    "天奈科技": "sh688116",
    "圣诺生物": "sh688117",
    "普元信息": "sh688118",
    "卓然股份": "sh688121",
    "西部超导": "sh688122",
    "聚辰股份": "sh688123",
    "沪硅产业": "sh688126",
    "蓝特光学": "sh688127",
    "中国电研": "sh688128",
    "东来技术": "sh688129",
    "皓元医药": "sh688131",
    "泰坦科技": "sh688133",
    "利扬芯片": "sh688135",
    "科兴制药": "sh688136",
    "清溢光电": "sh688138",
    "海尔生物": "sh688139",
    "芳源股份": "sh688148",
    "莱特光电": "sh688150",
    "华强科技": "sh688151",
    "先惠技术": "sh688155",
    "路德环境": "sh688156",
    "松井股份": "sh688157",
    "优刻得": "sh688158",
    "有方科技": "sh688159",
    "步科股份": "sh688160",
    "威高骨科": "sh688161",
    "巨一科技": "sh688162",
    "赛伦生物": "sh688163",
    "埃夫特": "sh688165",
    "博瑞医药": "sh688166",
    "炬光科技": "sh688167",
    "安博通": "sh688168",
    "石头科技": "sh688169",
    "纬德信息": "sh688171",
    "希荻微": "sh688173",
    "高凌信息": "sh688175",
    "亚虹医药": "sh688176",
    "百奥泰": "sh688177",
    "万德斯": "sh688178",
    "阿拉丁": "sh688179",
    "君实生物": "sh688180",
    "八亿时空": "sh688181",
    "灿勤科技": "sh688182",
    "生益电子": "sh688183",
    "康希诺": "sh688185",
    "广大特材": "sh688186",
    "时代电气": "sh688187",
    "柏楚电子": "sh688188",
    "南新制药": "sh688189",
    "云路股份": "sh688190",
    "智洋创新": "sh688191",
    "迪哲医药": "sh688192",
    "腾景科技": "sh688195",
    "卓越新能": "sh688196",
    "首药控股": "sh688197",
    "佰仁医疗": "sh688198",
    "久日新材": "sh688199",
    "华峰测控": "sh688200",
    "信安世纪": "sh688201",
    "美迪西": "sh688202",
    "概伦电子": "sh688206",
    "格灵深瞳": "sh688207",
    "道通科技": "sh688208",
    "统联精密": "sh688210",
    "中科微至": "sh688211",
    "澳华内镜": "sh688212",
    "瑞晟智能": "sh688215",
    "气派科技": "sh688216",
    "睿昂基因": "sh688217",
    "江苏北人": "sh688218",
    "会通股份": "sh688219",
    "翱捷科技": "sh688220",
    "前沿生物": "sh688221",
    "成都先导": "sh688222",
    "晶科能源": "sh688223",
    "亚信安全": "sh688225",
    "威腾电气": "sh688226",
    "品高股份": "sh688227",
    "开普云": "sh688228",
    "博睿数据": "sh688229",
    "芯导科技": "sh688230",
    "新点软件": "sh688232",
    "神工股份": "sh688233",
    "天岳先进": "sh688234",
    "百济神州": "sh688235",
    "春立医疗": "sh688236",
    "和元生物": "sh688238",
    "航宇科技": "sh688239",
    "嘉和美康": "sh688246",
    "南网科技": "sh688248",
    "凯尔达": "sh688255",
    "寒武纪": "sh688256",
    "新锐股份": "sh688257",
    "卓易信息": "sh688258",
    "创耀科技": "sh688259",
    "昀冢科技": "sh688260",
    "东微半导": "sh688261",
    "国芯科技": "sh688262",
    "南模生物": "sh688265",
    "泽璟制药": "sh688266",
    "中触媒": "sh688267",
    "华特气体": "sh688268",
    "凯立新材": "sh688269",
    "臻镭科技": "sh688270",
    "富吉瑞": "sh688272",
    "百克生物": "sh688276",
    "天智航": "sh688277",
    "特宝生物": "sh688278",
    "精进电动": "sh688280",
    "华秦科技": "sh688281",
    "理工导航": "sh688282",
    "坤恒顺维": "sh688283",
    "高铁电气": "sh688285",
    "敏芯股份": "sh688286",
    "鸿泉物联": "sh688288",
    "圣湘生物": "sh688289",
    "和达科技": "sh688296",
    "东方生物": "sh688298",
    "长阳科技": "sh688299",
    "联瑞新材": "sh688300",
    "奕瑞科技": "sh688301",
    "大全能源": "sh688303",
    "科德数控": "sh688305",
    "均普智能": "sh688306",
    "欧科亿": "sh688308",
    "恒誉环保": "sh688309",
    "迈得医疗": "sh688310",
    "盟升电子": "sh688311",
    "燕麦科技": "sh688312",
    "仕佳光子": "sh688313",
    "康拓医疗": "sh688314",
    "诺禾致源": "sh688315",
    "青云科技": "sh688316",
    "之江生物": "sh688317",
    "财富趋势": "sh688318",
    "欧林生物": "sh688319",
    "微芯生物": "sh688321",
    "瑞华泰": "sh688323",
    "深科达": "sh688328",
    "艾隆科技": "sh688329",
    "宏力达": "sh688330",
    "铂力特": "sh688333",
    "复洁环保": "sh688335",
    "三生国健": "sh688336",
    "赛科希德": "sh688338",
    "亿华通": "sh688339",
    "博力威": "sh688345",
    "富淼科技": "sh688350",
    "明志科技": "sh688355",
    "键凯科技": "sh688356",
    "建龙微纳": "sh688357",
    "祥生医疗": "sh688358",
    "三孚新科": "sh688359",
    "德马科技": "sh688360",
    "华熙生物": "sh688363",
    "光云科技": "sh688365",
    "昊海生科": "sh688366",
    "工大高科": "sh688367",
    "晶丰明源": "sh688368",
    "致远互联": "sh688369",
    "迪威尔": "sh688377",
    "奥来德": "sh688378",
    "华光新材": "sh688379",
    "新益昌": "sh688383",
    "复旦微电": "sh688385",
    "泛亚微透": "sh688386",
    "嘉元科技": "sh688388",
    "普门科技": "sh688389",
    "固德威": "sh688390",
    "安必平": "sh688393",
    "正弦电气": "sh688395",
    "华润微": "sh688396",
    "赛特新材": "sh688398",
    "硕世生物": "sh688399",
    "中信博": "sh688408",
    "震有科技": "sh688418",
    "铁建重工": "sh688425",
    "有研粉材": "sh688456",
    "金科环境": "sh688466",
    "科美诊断": "sh688468",
    "艾迪药业": "sh688488",
    "利元亨": "sh688499",
    "慧辰股份": "sh688500",
    "青达环保": "sh688501",
    "复旦张江": "sh688505",
    "芯朋微": "sh688508",
    "正元地信": "sh688509",
    "航亚科技": "sh688510",
    "天微电子": "sh688511",
    "苑东生物": "sh688513",
    "奥特维": "sh688516",
    "金冠电气": "sh688517",
    "联赢激光": "sh688518",
    "南亚新材": "sh688519",
    "神州细胞": "sh688520",
    "芯原股份": "sh688521",
    "科前生物": "sh688526",
    "秦川物联": "sh688528",
    "豪森股份": "sh688529",
    "上声电子": "sh688533",
    "思瑞浦": "sh688536",
    "和辉光电": "sh688538",
    "瑞联新材": "sh688550",
    "科威尔": "sh688551",
    "汇宇制药": "sh688553",
    "泽达易盛": "sh688555",
    "高测股份": "sh688556",
    "兰剑智能": "sh688557",
    "国盛智科": "sh688558",
    "海目星": "sh688559",
    "明冠新材": "sh688560",
    "奇安信": "sh688561",
    "力源科技": "sh688565",
    "吉贝尔": "sh688566",
    "孚能科技": "sh688567",
    "中科星图": "sh688568",
    "铁科轨道": "sh688569",
    "杭华股份": "sh688571",
    "亚辉龙": "sh688575",
    "浙海德曼": "sh688577",
    "艾力斯": "sh688578",
    "山大地纬": "sh688579",
    "伟思医疗": "sh688580",
    "上纬新材": "sh688585",
    "江航装备": "sh688586",
    "凌志软件": "sh688588",
    "力合微": "sh688589",
    "新致软件": "sh688590",
    "芯海科技": "sh688595",
    "正帆科技": "sh688596",
    "煜邦电力": "sh688597",
    "金博股份": "sh688598",
    "天合光能": "sh688599",
    "皖仪科技": "sh688600",
    "力芯微": "sh688601",
    "奥泰生物": "sh688606",
    "康众医疗": "sh688607",
    "恒玄科技": "sh688608",
    "九联科技": "sh688609",
    "杭州柯林": "sh688611",
    "奥精医疗": "sh688613",
    "西力科技": "sh688616",
    "惠泰医疗": "sh688617",
    "三旺通信": "sh688618",
    "罗普特": "sh688619",
    "阳光诺和": "sh688621",
    "禾信仪器": "sh688622",
    "呈和科技": "sh688625",
    "翔宇医疗": "sh688626",
    "优利德": "sh688628",
    "芯碁微装": "sh688630",
    "星球石墨": "sh688633",
    "智明达": "sh688636",
    "华恒生物": "sh688639",
    "迅捷兴": "sh688655",
    "浩欧博": "sh688656",
    "悦康药业": "sh688658",
    "元琛科技": "sh688659",
    "电气风电": "sh688660",
    "和林微纳": "sh688661",
    "富信科技": "sh688662",
    "新风光": "sh688663",
    "四方光电": "sh688665",
    "菱电电控": "sh688667",
    "鼎通科技": "sh688668",
    "聚石化学": "sh688669",
    "金迪克": "sh688670",
    "金盘科技": "sh688676",
    "海泰新光": "sh688677",
    "福立旺": "sh688678",
    "通源环境": "sh688679",
    "海优新材": "sh688680",
    "科汇股份": "sh688681",
    "霍莱沃": "sh688682",
    "莱尔科技": "sh688683",
    "迈信林": "sh688685",
    "奥普特": "sh688686",
    "凯因科技": "sh688687",
    "银河微电": "sh688689",
    "纳微科技": "sh688690",
    "极米科技": "sh688696",
    "纽威数控": "sh688697",
    "伟创电气": "sh688698",
    "明微电子": "sh688699",
    "东威科技": "sh688700",
    "卓锦股份": "sh688701",
    "振华新材": "sh688707",
    "宏微科技": "sh688711",
    "唯赛勃": "sh688718",
    "同益中": "sh688722",
    "格科微": "sh688728",
    "壹石通": "sh688733",
    "中自科技": "sh688737",
    "成大生物": "sh688739",
    "普冉股份": "sh688766",
    "博拓生物": "sh688767",
    "容知日新": "sh688768",
    "珠海冠宇": "sh688772",
    "国光电气": "sh688776",
    "中控技术": "sh688777",
    "厦钨新能": "sh688778",
    "长远锂科": "sh688779",
    "悦安新材": "sh688786",
    "海天瑞声": "sh688787",
    "科思科技": "sh688788",
    "宏华数科": "sh688789",
    "倍轻松": "sh688793",
    "艾为电子": "sh688798",
    "华纳药厂": "sh688799",
    "瑞可达": "sh688800",
    "天能股份": "sh688819",
    "中芯国际": "sh688981",
    "九号公司": "sh689009"
}